setup.py
pyhusmow/__init__.py
pyhusmow/husmow.py
pyhusmow/status_logger.py
pyhusmow.egg-info/PKG-INFO
pyhusmow.egg-info/SOURCES.txt
pyhusmow.egg-info/dependency_links.txt
pyhusmow.egg-info/entry_points.txt
pyhusmow.egg-info/not-zip-safe
pyhusmow.egg-info/requires.txt
pyhusmow.egg-info/top_level.txt