Metadata-Version: 1.0
Name: pyhusmow
Version: 0.2.0
Summary: Control your Husqvarna automower using Automower connect API.
Home-page: https://github.com/chrisz/pyhusmow
Author: Christophe Carre
Author-email: UNKNOWN
License: GPLv3
Platform: UNKNOWN
